CHANGES.txt
LICENSE.txt
MANIFEST.in
README.rst
setup.py
bin/mcb
bin/mcb-gui
mcb/__init__.py
mcb/config.py
mcb/runner.py
mycloudbackup.egg-info/PKG-INFO
mycloudbackup.egg-info/SOURCES.txt
mycloudbackup.egg-info/dependency_links.txt
mycloudbackup.egg-info/requires.txt
mycloudbackup.egg-info/top_level.txt