Metadata-Version: 1.0
Name: mycloudbackup
Version: 0.1.0
Summary: Back up data the cloud services you use
Home-page: https://github.com/theduke/mycloudbackup
Author: Christoph Herzog
Author-email: chris@theduke.at
License: New BSD License
Platform: UNKNOWN
